Metadata-Version: 1.0
Name: tcrCli
Version: 1.0
Summary: This is a sample cli for tcr
Home-page: UNKNOWN
Author: tcr-001181
Author-email: UNKNOWN
License: UNKNOWN
Platform: UNKNOWN
